pyhdfs.py
PythonWebHDFS-0.2.3.dist-info/DESCRIPTION.rst
PythonWebHDFS-0.2.3.dist-info/METADATA
PythonWebHDFS-0.2.3.dist-info/RECORD
PythonWebHDFS-0.2.3.dist-info/WHEEL
PythonWebHDFS-0.2.3.dist-info/metadata.json
PythonWebHDFS-0.2.3.dist-info/top_level.txt
