Metadata-Version: 1.1
Name: PythonWebHDFS
Version: 0.2.3
Summary: Customized Python Web HDFS client
Home-page: UNKNOWN
Author: SparkSnail
Author-email: noreplay@gmail.com
License: MIT License
Platform: UNKNOWN
Classifier: Intended Audience :: Developers
Classifier: License :: OSI Approved :: MIT License
Classifier: Operating System :: OS Independent
Classifier: Programming Language :: Python
Classifier: Programming Language :: Python :: 2
Classifier: Programming Language :: Python :: 3
Classifier: Topic :: System :: Filesystems
